MANIFEST.in
README.rst
setup.cfg
setup.py
translate
googletrans/__init__.py
googletrans/adapters.py
googletrans/client.py
googletrans/compat.py
googletrans/constants.py
googletrans/gtoken.py
googletrans/models.py
googletrans/urls.py
googletrans/utils.py
googletrans2.egg-info/PKG-INFO
googletrans2.egg-info/SOURCES.txt
googletrans2.egg-info/dependency_links.txt
googletrans2.egg-info/requires.txt
googletrans2.egg-info/top_level.txt